django_keycloak_lma/__init__.py
django_keycloak_lma/app_settings.py
django_keycloak_lma/apps.py
django_keycloak_lma/factories.py
django_keycloak_lma/hashers.py
django_keycloak_lma/middleware.py
django_keycloak_lma/models.py
django_keycloak_lma/remote_user.py
django_keycloak_lma/response.py
django_keycloak_lma/serializers.py
django_keycloak_lma/urls.py
django_keycloak_lma/views.py
django_keycloak_lma/admin/__init__.py
django_keycloak_lma/admin/realm.py
django_keycloak_lma/admin/server.py
django_keycloak_lma/auth/__init__.py
django_keycloak_lma/auth/backends.py
django_keycloak_lma/auth/permissions.py
django_keycloak_lma/base/__init__.py
django_keycloak_lma/base/authz.py
django_keycloak_lma/base/client.py
django_keycloak_lma/base/exceptions.py
django_keycloak_lma/base/mixins.py
django_keycloak_lma/base/openid_connect.py
django_keycloak_lma/base/realm.py
django_keycloak_lma/base/uma.py
django_keycloak_lma/base/uma1.py
django_keycloak_lma/base/well_known.py
django_keycloak_lma/base/admin/__init__.py
django_keycloak_lma/base/admin/clientroles.py
django_keycloak_lma/base/admin/clients.py
django_keycloak_lma/base/admin/groups.py
django_keycloak_lma/base/admin/realm.py
django_keycloak_lma/base/admin/users.py
django_keycloak_lma/base/admin/user/__init__.py
django_keycloak_lma/base/admin/user/usergroup.py
django_keycloak_lma/base/admin/user/userroles.py
django_keycloak_lma/base/aio/__init__.py
django_keycloak_lma/base/aio/abc.py
django_keycloak_lma/base/aio/authz.py
django_keycloak_lma/base/aio/client.py
django_keycloak_lma/base/aio/mixins.py
django_keycloak_lma/base/aio/openid_connect.py
django_keycloak_lma/base/aio/realm.py
django_keycloak_lma/base/aio/uma.py
django_keycloak_lma/base/aio/well_known.py
django_keycloak_lma/migrations/0001_initial.py
django_keycloak_lma/migrations/0002_auto_20180322_2059.py
django_keycloak_lma/migrations/0003_auto_20190204_1949.py
django_keycloak_lma/migrations/0004_client_service_account_profile.py
django_keycloak_lma_cut-0.1.7.dist-info/METADATA
django_keycloak_lma_cut-0.1.7.dist-info/WHEEL
django_keycloak_lma_cut-0.1.7.dist-info/top_level.txt
django_keycloak_lma_cut-0.1.7.dist-info/RECORD
