Metadata-Version: 2.1
Name: django_keycloak_lma_cut
Version: 0.1.7
Summary: Cut down version of the package django_keycloak_lma
Author: Vyacheslav Konovalov
Requires-Dist: djangorestframework
